xsum.cpython-311-darwin.so
tests/__init__.py
tests/__main__.py
tests/test_xsum/__init__.py
tests/test_xsum/__main__.py
tests/test_xsum/test_xsum.py
xsum-1.1.8.dist-info/LICENSE
xsum-1.1.8.dist-info/METADATA
xsum-1.1.8.dist-info/WHEEL
xsum-1.1.8.dist-info/top_level.txt
xsum-1.1.8.dist-info/RECORD
