Metadata-Version: 2.1
Name: xsum
Version: 1.1.8
Summary: Fast Exact Summation Using Small and Large Superaccumulators
Home-page: https://github.com/yafshar/xsum
Author: Yaser Afshar
Author-email: ya.afshar@gmail.com
License: LGPLv2
Keywords: xsum
Classifier: Development Status :: 5 - Production/Stable
Classifier: Intended Audience :: Science/Research
Classifier: Topic :: Scientific/Engineering
Classifier: Operating System :: OS Independent
Classifier: License :: OSI Approved :: GNU Lesser General Public License v2 (LGPLv2)
License-File: LICENSE
Requires-Dist: numpy
